LICENSE.txt
MANIFEST.in
README.md
setup.py
PyCommons/DictObject.py
PyCommons/Encodings.py
PyCommons/GetPass.py
PyCommons/Logs.py
PyCommons/PrintF.py
PyCommons/Process.py
PyCommons/Report.py
PyCommons/StringF.py
PyCommons/Terminal.py
PyCommons/TestTimeout.py
PyCommons/Timeout.py
PyCommons/__init__.py
PyCommons/cleandict.py
PyCommons/urlopen.py
PythonToolsKit.egg-info/PKG-INFO
PythonToolsKit.egg-info/SOURCES.txt
PythonToolsKit.egg-info/dependency_links.txt
PythonToolsKit.egg-info/top_level.txt