Metadata-Version: 2.1
Name: PythonToolsKit
Version: 0.0.1
Summary:  This package implements tools to build python package and tools. 
Home-page: https://github.com/mauricelambert/PyCommons
Author: Maurice Lambert
Author-email: mauricelambert434@gmail.com
Maintainer: Maurice Lambert
Maintainer-email: mauricelambert434@gmail.com
License: GPL-3.0 License
Project-URL: Documentation Timeout, https://mauricelambert.github.io/info/python/code/PyCommons/Timeout.html
Project-URL: Documentation Terminal, https://mauricelambert.github.io/info/python/code/PyCommons/Terminal.html
Project-URL: Documentation StringF, https://mauricelambert.github.io/info/python/code/PyCommons/StringF.html
Project-URL: Documentation PrintF, https://mauricelambert.github.io/info/python/code/PyCommons/PrintF.html
Project-URL: Documentation Process, https://mauricelambert.github.io/info/python/code/PyCommons/Process.html
Project-URL: Documentation Logs, https://mauricelambert.github.io/info/python/code/PyCommons/Logs.html
Project-URL: Documentation GetPass, https://mauricelambert.github.io/info/python/code/PyCommons/GetPass.html
Project-URL: Documentation Encodings, https://mauricelambert.github.io/info/python/code/PyCommons/Encodings.html
Project-URL: Documentation DictObject, https://mauricelambert.github.io/info/python/code/PyCommons/DictObject.html
Project-URL: Documentation Report, https://mauricelambert.github.io/info/python/code/PyCommons/Report.html
Project-URL: Documentation urlopen, https://mauricelambert.github.io/info/python/code/PyCommons/urlopen.html
Project-URL: Documentation cleandict, https://mauricelambert.github.io/info/python/code/PyCommons/cleandict.html
Keywords: Timeout,Terminal,Colors,Formatting,Print,Object,Process,CSV,Logs,Getpass,Password,Ask,*,Encodings,Report,Markdown,HTML,JSON
Platform: Windows
Platform: Linux
Platform: MacOS
Classifier: Programming Language :: Python
Classifier: Development Status :: 5 - Production/Stable
Classifier: Natural Language :: English
Classifier: Programming Language :: Python :: 3.9
Classifier: Operating System :: POSIX :: Linux
Classifier: Operating System :: Microsoft :: Windows
Classifier: Operating System :: MacOS
Requires-Python: >=3.6
License-File: LICENSE.txt
